{
  "kitsuId": "56313",
  "title": "Eiyuu no Musume toshite Umarekawatta Eiyuu wa Futatabi Eiyuu wo Mezasu",
  "updatedAt": "2026-07-18T22:06:37.384Z",
  "matchVersion": 2,
  "mangabakaId": 9960,
  "mangabakaUrl": "https://mangabaka.org/9960",
  "match": {
    "confidence": "verified",
    "method": "kitsu-link",
    "score": 100
  },
  "cover": "https://cdn.mangabaka.dev/imgproxy/plain/x350@2/aHR0cHM6Ly9pbWFnZXMubWFuZ2FiYWthLmRldi85LzkvYi80LzMvYi8yLzEvODFmMC80MWU4LzhmN2EvYzRkNWFhY2MxM2M1",
  "author": "Amane Kotodera, Haruka Kaburagi",
  "synopsis": "Reid, one of the six great heroes of legend, lost his life during a fight with a demon. Floating around in the afterlife, he met a suspicious god who assured that he would live once again. When Reid opened his eyes, he discovered that he was reborn as a baby. Moreover, as the daughter of his former fellow comrades. \n\nWhile Reid initially struggled to become a hero in his former life due to his half-demon heritage, he realizes that he has been reborn as the daughter of the legendary hero and the powerful saint. With the experience he gained from his past life, as well as the talents inherited from his parents, Nicole aims to become a hero yet again. \n\n*Note: Chapter count includes four extras from the volume release.*",
  "status": "Completed",
  "rating": 6.5,
  "total": 28,
  "type": "manga",
  "genres": [
    "action",
    "adventure",
    "comedy",
    "fantasy",
    "gender_bender",
    "yuri"
  ],
  "tags": [
    {
      "name": "Shounen",
      "group": "Audience Demographics",
      "weight": "defining"
    },
    {
      "name": "Hero",
      "group": "Character Archetype",
      "weight": "core"
    },
    {
      "name": "Heterochromia",
      "group": "Character Traits",
      "weight": "recurrent"
    },
    {
      "name": "Female Lead",
      "group": "Character Types",
      "weight": "defining"
    },
    {
      "name": "Young Female Lead",
      "group": "Character Types",
      "weight": "recurrent"
    },
    {
      "name": "Based on a Light Novel",
      "group": "Derivative Work",
      "weight": "unweighted"
    },
    {
      "name": "Based on a Novel",
      "group": "Derivative Work",
      "weight": "defining"
    },
    {
      "name": "Gender Bender",
      "group": "Narrative Tropes",
      "weight": "defining"
    },
    {
      "name": "Saving the World",
      "group": "Narrative Tropes",
      "weight": "unweighted"
    },
    {
      "name": "Reincarnation",
      "group": "Narrative Tropes",
      "weight": "recurrent"
    },
    {
      "name": "Fantasy",
      "group": "Genre",
      "weight": "defining"
    },
    {
      "name": "Fantasy World",
      "group": "Settings",
      "weight": "core"
    },
    {
      "name": "Ecchi",
      "group": "Sexual Content",
      "weight": "unweighted"
    },
    {
      "name": "Demons",
      "group": "Species & Creatures",
      "weight": "unweighted"
    },
    {
      "name": "Action",
      "group": "Genre",
      "weight": "defining"
    },
    {
      "name": "Adventure",
      "group": "Genre",
      "weight": "defining"
    },
    {
      "name": "Comedy",
      "group": "Genre",
      "weight": "defining"
    },
    {
      "name": "Yuri",
      "group": "Themes",
      "weight": "defining"
    },
    {
      "name": "Magic",
      "group": "World Building",
      "weight": "core"
    }
  ],
  "news": [],
  "sources": {
    "anilist": "101730",
    "anime_planet": "eiyuu-no-musume-to-shite-umarekawatta-eiyuu-wa-futatabi-eiyuu-wo-mezasu",
    "anime_news_network": "21473",
    "kitsu": "56313",
    "manga_updates": "erqx84y",
    "my_anime_list": "116003",
    "shikimori": "116003"
  },
  "links": [
    "https://comic-walker.com/contents/detail/KDCW_MF00000063010000_68/",
    "https://mangabaka.org/9960"
  ]
}